notte/__init__.py
notte/py.typed
notte-1.8.3.dist-info/METADATA
notte-1.8.3.dist-info/WHEEL
notte-1.8.3.dist-info/licenses/LICENSE
notte-1.8.3.dist-info/RECORD
