Metadata-Version: 2.4
Name: notte
Version: 1.8.3
Summary: Notte, the full-stack web AI agent framework
Author-email: Notte Team  <hello@notte.cc>
License-Expression: SSPL-1.0
License-File: LICENSE
Requires-Python: >=3.11
Requires-Dist: google-auth>=2.39.0
Requires-Dist: notte-agent==v1.8.3
Requires-Dist: notte-browser==v1.8.3
Requires-Dist: notte-core==v1.8.3
Requires-Dist: notte-sdk==v1.8.3
Requires-Dist: toml>=0.10.2
Provides-Extra: eval
Requires-Dist: notte-eval==v1.8.3; extra == 'eval'
Provides-Extra: integrations
Requires-Dist: notte-integrations==v1.8.3; extra == 'integrations'
Provides-Extra: mcp
Requires-Dist: notte-mcp==v1.8.3; extra == 'mcp'
